hil/bus/__init__.py
hil/bus/utils.py
hil/common/__init__.py
hil/common/env.py
hil/common/exception.py
hil/common/log.py
hil/common/sleep_ns.py
hil/common/utils.py
hil/core/__init__.py
hil/core/bin.py
hil/core/cantp.cp39-win_amd64.pyd
hil/core/cantp.pyi
hil/core/doip_client.cp39-win_amd64.pyd
hil/core/doip_client.pyi
hil/core/doip_server.cp39-win_amd64.pyd
hil/core/doip_server.pyi
hil/core/uds_client.cp39-win_amd64.pyd
hil/core/uds_client.pyi
hil/core/uds_server.cp39-win_amd64.pyd
hil/core/uds_server.pyi
hil/dbc/__init__.py
hil/dbc/_canlib.py
hil/dbc/_cantools.py
hil/dbc/parser.py
hil/gp/__init__.py
hil/gp/__main__.py
hil/gp/bin.py
hil_core-0.0.8.post4.dist-info/METADATA
hil_core-0.0.8.post4.dist-info/WHEEL
hil_core-0.0.8.post4.dist-info/entry_points.txt
hil_core-0.0.8.post4.dist-info/top_level.txt
hil_core-0.0.8.post4.dist-info/RECORD
