Metadata-Version: 2.4
Name: hil-core
Version: 0.0.8.post4
Summary: Carota HIL核心库
Author: notmmao
Author-email: notmmao@gmail.com
License: Carota HIL License
Platform: windows
Requires-Python: >=3.6
Requires-Dist: python-can
Requires-Dist: can-isotp
Requires-Dist: termcolor
Requires-Dist: scapy
Requires-Dist: construct
Requires-Dist: requests
Requires-Dist: loguru
Requires-Dist: bsdiff4
Requires-Dist: pyyaml
Provides-Extra: dbc
Requires-Dist: cantools; extra == "dbc"
Dynamic: author
Dynamic: author-email
Dynamic: description
Dynamic: license
Dynamic: platform
Dynamic: provides-extra
Dynamic: requires-dist
Dynamic: requires-python
Dynamic: summary
